peerbridge/__init__.py
peerbridge/main.py
peerbridge/utils.py
peerbridge-0.2.0.dist-info/LICENSE
peerbridge-0.2.0.dist-info/METADATA
peerbridge-0.2.0.dist-info/WHEEL
peerbridge-0.2.0.dist-info/entry_points.txt
peerbridge-0.2.0.dist-info/top_level.txt
peerbridge-0.2.0.dist-info/RECORD
