Metadata-Version: 2.1
Name: peerbridge
Version: 0.2.0
Summary: A simple and secure peer-to-peer file transfer tool.
Home-page: https://github.com/Atharvatonape/PeerBridge
Author: Atharva Tonape
Author-email: athravtonape1001@gmail.com
Classifier: Programming Language :: Python :: 3
Classifier: License :: OSI Approved :: MIT License
Classifier: Operating System :: OS Independent
Requires-Python: >=3.6
License-File: LICENSE
Requires-Dist: pyminizip
